ctdpy/__init__.py
ctdpy/core/__init__.py
ctdpy/core/archive_handler.py
ctdpy/core/calculator.py
ctdpy/core/config.py
ctdpy/core/data_handlers.py
ctdpy/core/mapping.py
ctdpy/core/profile.py
ctdpy/core/session.py
ctdpy/core/utils.py
ctdpy/core/etc/destrete_depths.json
ctdpy/core/etc/mapping_parameter.json
ctdpy/core/etc/mapping_ship.json
ctdpy/core/etc/mapping_unit.json
ctdpy/core/etc/settings_paths.json
ctdpy/core/etc/readers/ctd_stdfmt.yaml
ctdpy/core/etc/readers/deep.yaml
ctdpy/core/etc/readers/nos.yaml
ctdpy/core/etc/readers/sgus.yaml
ctdpy/core/etc/readers/slua.yaml
ctdpy/core/etc/readers/smhi.yaml
ctdpy/core/etc/readers/umsc.yaml
ctdpy/core/etc/templates/archive_structure.yaml
ctdpy/core/etc/templates/ctd_metadata.yaml
ctdpy/core/etc/templates/phyche.yaml
ctdpy/core/etc/writers/ctd_standard_template.yaml
ctdpy/core/etc/writers/metadata_template.yaml
ctdpy/core/etc/writers/txt.yaml
ctdpy/core/etc/writers/xlsx.yaml
ctdpy/core/etc/writers/zip.yaml
ctdpy/core/readers/__init__.py
ctdpy/core/readers/cnv_reader.py
ctdpy/core/readers/deep.py
ctdpy/core/readers/file_handlers.py
ctdpy/core/readers/json_reader.py
ctdpy/core/readers/metadata.py
ctdpy/core/readers/mvp200.py
ctdpy/core/readers/nos.py
ctdpy/core/readers/rinco.py
ctdpy/core/readers/seabird.py
ctdpy/core/readers/sgus.py
ctdpy/core/readers/slua.py
ctdpy/core/readers/smhi.py
ctdpy/core/readers/stdfmt.py
ctdpy/core/readers/swift_svp.py
ctdpy/core/readers/txt_reader.py
ctdpy/core/readers/umsc.py
ctdpy/core/readers/xlsx_reader.py
ctdpy/core/readers/yaml_reader.py
ctdpy/core/templates/__init__.py
ctdpy/core/templates/ctd_metadata.py
ctdpy/core/templates/template.py
ctdpy/core/templates/xlsx_phyche.py
ctdpy/core/writers/__init__.py
ctdpy/core/writers/metadata.py
ctdpy/core/writers/standard_formats.py
ctdpy/core/writers/txt_writer.py
ctdpy/core/writers/with_style.py
ctdpy/core/writers/xlsx_writer.py
ctdpy/core/writers/yaml_writer.py
ctdpy/core/writers/zip_writer.py
ctdpy/templates/Format Physical and chemical.xlsx
ctdpy-0.1.7.dist-info/LICENSE.txt
ctdpy-0.1.7.dist-info/METADATA
ctdpy-0.1.7.dist-info/WHEEL
ctdpy-0.1.7.dist-info/top_level.txt
ctdpy-0.1.7.dist-info/RECORD
