Metadata-Version: 2.1
Name: ctdpy
Version: 0.1.7
Summary: Package to handle CTD data
Home-page: https://github.com/sharksmhi/ctdpy
Author: Johannes Johansson
Author-email: johannes.johansson@smhi.se
License: UNKNOWN
Platform: UNKNOWN
Classifier: Programming Language :: Python :: 3
Classifier: License :: OSI Approved :: MIT License
Classifier: Operating System :: OS Independent
Requires-Python: >=3.6
License-File: LICENSE.txt
Requires-Dist: numpy
Requires-Dist: pandas
Requires-Dist: gsw
Requires-Dist: seawater
Requires-Dist: trollsift
Requires-Dist: six
Requires-Dist: PyYAML
Requires-Dist: setuptools
